RoboSmartServo/SmartServo.py
RoboSmartServo/__init__.py
RoboSmartServo-0.0.1.dist-info/METADATA
RoboSmartServo-0.0.1.dist-info/WHEEL
RoboSmartServo-0.0.1.dist-info/top_level.txt
RoboSmartServo-0.0.1.dist-info/RECORD
