Metadata-Version: 2.1
Name: RoboSmartServo
Version: 0.0.1
Summary: Package for operating Smart Servos made by ROBOROBO in Seoul ROK
Home-page: https://github.com/pypa/sampleproject
Author: Example Author
Author-email: kimjunseob1@roborobo.co.kr
License: UNKNOWN
Platform: UNKNOWN
Classifier: Programming Language :: Python :: 3
Classifier: License :: OSI Approved :: MIT License
Classifier: Operating System :: OS Independent
Requires-Python: >=3.6
